LICENSE
README.md
setup.cfg
setup.py
arequestsHelper/__init__.py
arequestsHelper/arequestsHelper.py
arequestsHelper/errors.py
arequestsHelper.egg-info/PKG-INFO
arequestsHelper.egg-info/SOURCES.txt
arequestsHelper.egg-info/dependency_links.txt
arequestsHelper.egg-info/requires.txt
arequestsHelper.egg-info/top_level.txt