Metadata-Version: 2.1
Name: arequestsHelper
Version: 0.4.3
Summary: This pakage helps to work with aiohttp requests in many threads
Home-page: https://github.com/Harukvitalii
Download-URL: https://github.com/Harukvitalii/ArequestHelper/archive/refs/tags/v0.4.3.zip
Author: Vitalii Haruk
Author-email: garuk1vitalik@gmail.com
License: MIT
Keywords: aiohttp,requests,threads
Classifier: Development Status :: 3 - Alpha
Classifier: Intended Audience :: Developers
Classifier: Topic :: Software Development :: Build Tools
Classifier: License :: OSI Approved :: MIT License
Classifier: Programming Language :: Python :: 3
Classifier: Programming Language :: Python :: 3.4
Classifier: Programming Language :: Python :: 3.5
Classifier: Programming Language :: Python :: 3.6
License-File: LICENSE
